ninja_search/__init__.py
ninja_search/py.typed
ninja_search/searching.py
django_ninja_search-0.1.8.dist-info/LICENSE
django_ninja_search-0.1.8.dist-info/METADATA
django_ninja_search-0.1.8.dist-info/WHEEL
django_ninja_search-0.1.8.dist-info/RECORD
