Metadata-Version: 2.3
Name: django-ninja-search
Version: 0.1.8
Summary: A decorator to simplify searching and filtering in Django Ninja views.
Author: Anand R Nair
Author-email: anand547@outlook.com
Requires-Python: >=3.10
Classifier: Development Status :: 3 - Alpha
Classifier: Intended Audience :: Developers
Classifier: License :: OSI Approved :: MIT License
Classifier: Programming Language :: Python
Classifier: Programming Language :: Python :: 3
Classifier: Programming Language :: Python :: 3.10
Classifier: Programming Language :: Python :: 3.11
Classifier: Programming Language :: Python :: 3.12
Classifier: Programming Language :: Python :: 3.13
Classifier: Framework :: Django
Classifier: Framework :: Django :: 5.1
Classifier: Framework :: Django :: 5.2
Classifier: Operating System :: OS Independent
Classifier: Topic :: Software Development :: Libraries
Requires-Dist: django (>=5.0.0,<6.0.0)
Requires-Dist: django-ninja (>=1.0.0,<2.0.0)
